fasctreat/__init__.py
fasctreat/main.py
fasctreat-1.0.1.dist-info/LICENSE.txt
fasctreat-1.0.1.dist-info/METADATA
fasctreat-1.0.1.dist-info/WHEEL
fasctreat-1.0.1.dist-info/top_level.txt
fasctreat-1.0.1.dist-info/RECORD
