Metadata-Version: 2.1
Name: fasctreat
Version: 1.0.1
Summary: This is a project template.
Author: lylake
Classifier: Topic :: Software Development :: Libraries :: Python Modules
Classifier: Development Status :: 4 - Beta
Classifier: License :: OSI Approved :: MIT License
Classifier: Programming Language :: Python :: 3
Classifier: Programming Language :: Python :: 3.3
Classifier: Programming Language :: Python :: 3.4
Classifier: Programming Language :: Python :: 3.5
Classifier: Programming Language :: Python :: 3.6
Classifier: Programming Language :: Python :: 3.7
Classifier: Programming Language :: Python :: 3.8
Classifier: Programming Language :: Python :: 3.9
Classifier: Operating System :: Microsoft :: Windows
Classifier: Intended Audience :: End Users/Desktop
Classifier: Natural Language :: English
Classifier: Natural Language :: Chinese (Simplified)
License-File: LICENSE.txt
Requires-Dist: numpy ==1.23.5
